monai/deploy/__init__.py
monai/deploy/_version.py
monai/deploy/_version_1.0.py
monai/deploy/exceptions.py
monai/deploy/logging.json
monai/deploy/py.typed
monai/deploy/conditions/__init__.py
monai/deploy/core/__init__.py
monai/deploy/core/app_context.py
monai/deploy/core/arg_parser.py
monai/deploy/core/io_type.py
monai/deploy/core/runtime_env.py
monai/deploy/core/version.py
monai/deploy/core/datastores/__init__.py
monai/deploy/core/datastores/datastore.py
monai/deploy/core/datastores/factory.py
monai/deploy/core/datastores/memory.py
monai/deploy/core/domain/__init__.py
monai/deploy/core/domain/datapath.py
monai/deploy/core/domain/dicom_series.py
monai/deploy/core/domain/dicom_series_selection.py
monai/deploy/core/domain/dicom_sop_instance.py
monai/deploy/core/domain/dicom_study.py
monai/deploy/core/domain/domain.py
monai/deploy/core/domain/image.py
monai/deploy/core/models/__init__.py
monai/deploy/core/models/factory.py
monai/deploy/core/models/model.py
monai/deploy/core/models/named_model.py
monai/deploy/core/models/torch_model.py
monai/deploy/core/models/triton_model.py
monai/deploy/executors/__init__.py
monai/deploy/graphs/__init__.py
monai/deploy/logger/__init__.py
monai/deploy/operators/__init__.py
monai/deploy/operators/clara_viz_operator.py
monai/deploy/operators/decoder_nvimgcodec.py
monai/deploy/operators/dicom_data_loader_operator.py
monai/deploy/operators/dicom_encapsulated_pdf_writer_operator.py
monai/deploy/operators/dicom_seg_writer_operator.py
monai/deploy/operators/dicom_seg_writer_operator_all_frames_to_delete.py
monai/deploy/operators/dicom_series_selector_operator.py
monai/deploy/operators/dicom_series_to_volume_operator.py
monai/deploy/operators/dicom_text_sr_writer_operator.py
monai/deploy/operators/dicom_utils.py
monai/deploy/operators/inference_operator.py
monai/deploy/operators/monai_bundle_inference_operator.py
monai/deploy/operators/monai_seg_inference_operator.py
monai/deploy/operators/nii_data_loader_operator.py
monai_deploy_app_sdk-3.5.0.dist-info/licenses/LICENSE
monai_deploy_app_sdk-3.5.0.dist-info/METADATA
monai_deploy_app_sdk-3.5.0.dist-info/WHEEL
monai_deploy_app_sdk-3.5.0.dist-info/top_level.txt
monai_deploy_app_sdk-3.5.0.dist-info/RECORD
