Metadata-Version: 2.4
Name: monai-deploy-app-sdk
Version: 3.5.0
Summary: A framework and associated tools to design, verify and analyze performance of MONAI apps
Home-page: https://github.com/Project-MONAI/
Author: MONAI Consortium
Author-email: monai.contact@gmail.com
License: Apache License 2.0
Project-URL: Documentation, https://project-monai.github.io/deploy.html
Project-URL: Bug Tracker, https://github.com/Project-MONAI/monai-deploy-app-sdk/issues
Project-URL: Source Code, https://github.com/Project-MONAI/monai-deploy-app-sdk
Platform: OS Independent
Requires-Python: <3.14,>=3.10
License-File: LICENSE
Requires-Dist: numpy>=1.21.6
Requires-Dist: holoscan-cu12
Requires-Dist: holoscan-cli
Requires-Dist: colorama>=0.4.1
Requires-Dist: tritonclient[all]>=2.53.0
Requires-Dist: typeguard>=3.0.0
Provides-Extra: all
Requires-Dist: cucim~=21.06; extra == "all"
Provides-Extra: cucim
Requires-Dist: cucim~=21.06; extra == "cucim"
Dynamic: license-file
